affiliation_regex_parser/__init__.py
affiliation_regex_parser/_version.py
affiliation_regex_parser/city2country.py
affiliation_regex_parser/keyword_city_list.py
affiliation_regex_parser/keyword_country_list.py
affiliation_regex_parser/keywords_patterns.py
affiliation_regex_parser/parser.py
affiliation_regex_parser/providers.py
affiliation_regex_parser/data/worldcities.xlsx
affiliation_regex_parser-0.1.0.dist-info/licenses/LICENSE
affiliation_regex_parser-0.1.0.dist-info/METADATA
affiliation_regex_parser-0.1.0.dist-info/WHEEL
affiliation_regex_parser-0.1.0.dist-info/top_level.txt
affiliation_regex_parser-0.1.0.dist-info/RECORD
