Metadata-Version: 2.4
Name: affiliation-regex-parser
Version: 0.1.0
Summary: Regex-based parser for structuring academic author affiliation strings.
Author-email: Ehsan Bitaraf <ehsan.bitaraf@gmail.com>
License: MIT
Project-URL: Homepage, https://github.com/EhsanBitaraf/affiliation-regex-parser
Project-URL: Repository, https://github.com/EhsanBitaraf/affiliation-regex-parser
Project-URL: Issues, https://github.com/EhsanBitaraf/affiliation-regex-parser/issues
Keywords: affiliation,parser,regex,nlp,metadata,academia
Classifier: License :: OSI Approved :: MIT License
Classifier: Programming Language :: Python :: 3
Classifier: Programming Language :: Python :: 3 :: Only
Classifier: Programming Language :: Python :: 3.10
Classifier: Programming Language :: Python :: 3.11
Classifier: Programming Language :: Python :: 3.12
Classifier: Intended Audience :: Science/Research
Classifier: Topic :: Text Processing :: Linguistic
Classifier: Topic :: Scientific/Engineering :: Information Analysis
Classifier: Operating System :: OS Independent
Requires-Python: >=3.10
License-File: LICENSE
Requires-Dist: flashtext>=2.7
Provides-Extra: excel
Requires-Dist: pandas>=2.0; extra == "excel"
Requires-Dist: openpyxl>=3.1; extra == "excel"
Dynamic: license-file
